tcod/ecs/__init__.py
tcod/ecs/_converter.py
tcod/ecs/_version.py
tcod/ecs/callbacks.py
tcod/ecs/constants.py
tcod/ecs/entity.py
tcod/ecs/py.typed
tcod/ecs/query.py
tcod/ecs/registry.py
tcod/ecs/typing.py
tcod/ecs/world.py
tcod_ecs-5.5.0.dist-info/licenses/LICENSE
tcod_ecs-5.5.0.dist-info/WHEEL
tcod_ecs-5.5.0.dist-info/METADATA
tcod_ecs-5.5.0.dist-info/RECORD
