Metadata-Version: 2.4
Name: tcod-ecs
Version: 5.5.0
Summary: A type-hinted Entity Component System based on Python dictionaries and sets.
Author-email: Kyle Benesch <4b796c65+github@gmail.com>
Requires-Python: >=3.10
Classifier: Development Status :: 5 - Production/Stable
Classifier: Intended Audience :: Developers
Classifier: License :: OSI Approved :: MIT License
Classifier: Operating System :: OS Independent
Classifier: Programming Language :: Python :: 3
Classifier: Topic :: Software Development :: Libraries :: Python Modules
Classifier: Typing :: Typed
License-File: LICENSE
Requires-Dist: attrs >=23.1.0
Requires-Dist: cattrs >=23.1.2
Requires-Dist: typing-extensions >=4.14.0
Requires-Dist: attrs >=22.2.0 ; extra == "test"
Requires-Dist: pytest >=7.2.0 ; extra == "test"
Requires-Dist: pytest-cov >=4.0.0 ; extra == "test"
Requires-Dist: pytest-benchmark >=4.0.0 ; extra == "test"
Requires-Dist: mypy >=1.17.0 ; extra == "test"
Project-URL: Changelog, https://github.com/HexDecimal/python-tcod-ecs/blob/main/CHANGELOG.md
Project-URL: Documentation, https://python-tcod-ecs.readthedocs.io
Project-URL: Home, https://github.com/HexDecimal
Project-URL: Source, https://github.com/HexDecimal/python-tcod-ecs
Provides-Extra: test
